{
  "AF": "افغانستان",
  "AX": "جزایر آلند",
  "AL": "آلبانی",
  "DZ": "الجزایر",
  "AS": "ساموا",
  "AD": "آندورا",
  "AO": "آنگولا",
  "AI": "آنگویلا",
  "AQ": "قطب جنوب",
  "AG": "آنتیگوا و باربودا",
  "AR": "آرژانتین",
  "AM": "ارمنستان",
  "AW": "آروبا",
  "AU": "استرالیا",
  "AT": "اتریش",
  "AZ": "آذربایجان",
  "BS": "باهاما",
  "BH": "بحرین",
  "BD": "بنگلادش",
  "BB": "باربادوس",
  "BY": "بلاروس",
  "BE": "بلژیک",
  "BZ": "بلیز",
  "BJ": "بنین",
  "BM": "برمودا",
  "BT": "بوتان",
  "BO": "بولیوی (Plurinational State of)",
  "BQ": "بونیر سنت Eustatius and Saba",
  "BA": "بوسنی و هرزگوین",
  "BW": "بوتسوانا",
  "BV": "جزیره بووه",
  "BR": "برزیل",
  "IO": "قلمرو بریتانیا در اقیانوس هند",
  "BN": "برونئی",
  "BG": "بلغارستان",
  "BF": "بورکینافاسو",
  "BI": "بوروندی",
  "CV": "Cabo Verde",
  "KH": "کامبوج",
  "CM": "کامرون",
  "CA": "کانادا",
  "KY": "جزایر کیمن",
  "CF": "جمهوری آفریقای مرکزی",
  "TD": "چاد",
  "CL": "شیلی",
  "CN": "چین",
  "CX": "جزیره کریسمس",
  "CC": "Cocos (Keeling) Islands",
  "CO": "کلمبیا",
  "KM": "کومور",
  "CG": "کنگو",
  "CD": "کنگو (جمهوری دموکراتیک)",
  "CK": "جزایر کوک",
  "CR": "کاستاریکا",
  "CI": "ساحل عاج",
  "HR": "کرواسی",
  "CU": "کوبا",
  "CW": "ویدیو",
  "CY": "قبرس",
  "CZ": "جمهوری چک",
  "DK": "دانمارک",
  "DJ": "جیبوتی",
  "DM": "دومینیکا",
  "DO": "جمهوری دومینیکن",
  "EC": "اکوادور",
  "EG": "مصر",
  "SV": "ال سالوادور",
  "GQ": "گینه استوایی",
  "ER": "اریتره",
  "EE": "استونی",
  "ET": "اتیوپی",
  "FK": "جزایر فالکلند (مالویناس)",
  "FO": "جزایر فارو",
  "FJ": "فیجی",
  "FI": "فنلاند",
  "FR": "فرانسه",
  "GF": "گویان فرانسه",
  "PF": "پلینزی فرانسه",
  "TF": "French Southern Territories",
  "GA": "گابن",
  "GM": "گامبیا",
  "GE": "گرجستان",
  "DE": "آلمان",
  "GH": "غنا",
  "GI": "جبل الطارق",
  "GR": "یونان",
  "GL": "گرینلند",
  "GD": "گرانادا",
  "GP": "جزیره گوادلوپ",
  "GU": "گوام",
  "GT": "گواتمالا",
  "GG": "گورنسی",
  "GN": "گینه",
  "GW": "گینه بیسائو",
  "GY": "گویان",
  "HT": "هائیتی",
  "HM": "جزیره هرد و جزایر مک دونالد",
  "VA": "مقدس",
  "HN": "هندوراس",
  "HK": "دلار هنگ کنگ",
  "HU": "مجارستان",
  "IS": "ایسلند",
  "IN": "هند",
  "ID": "اندونزی",
  "IR": "ایران (جمهوری اسلامی)",
  "IQ": "عراق",
  "IE": "ایرلند",
  "IM": "جزیره من",
  "IL": "اسرائیل",
  "IT": "ایتالیا",
  "JM": "جامائیکا",
  "JP": "ژاپن",
  "JE": "نیوجرسی",
  "JO": "اردن",
  "KZ": "قزاقستان",
  "KE": "کنیا",
  "KI": "کیریباتی",
  "KP": "کره جنوبی (جمهوری دموکراتیک خلق)",
  "KR": "کره جنوبی (جمهوری)",
  "KW": "کویت",
  "KG": "قرقیزستان",
  "LA": "جمهوری دموکراتیک خلق لائو",
  "LV": "لتونی",
  "LB": "لبنان",
  "LS": "لسوتو",
  "LR": "لیبریا",
  "LY": "لیبی",
  "LI": "لیختن اشتاین",
  "LT": "لیتوانی",
  "LU": "لوکزامبورگ",
  "MO": "ماکائو",
  "MK": "مقدونیه (جمهوری سابق یوگسلاوی)",
  "MG": "ماداگاسکار",
  "MW": "مالاوی",
  "MY": "مالزی",
  "MV": "مالدیو",
  "ML": "مالی",
  "MT": "مالت",
  "MH": "جزایر مارشال",
  "MQ": "مارتینیک",
  "MR": "موریتانی",
  "MU": "موریس",
  "YT": "Mayotte",
  "MX": "مکزیک",
  "FM": "میکرونزی (پرنسیپ)",
  "MD": "مولداوی (جمهوری)",
  "MC": "موناکو",
  "MN": "مغولستان",
  "ME": "مونته نگرو",
  "MS": "مونتسرات",
  "MA": "مراکش",
  "MZ": "موزامبیک",
  "MM": "میانمار",
  "NA": "نامیبیا",
  "NR": "نائورو",
  "NP": "نپال",
  "NL": "هلند",
  "NC": "کالدونیای جدید",
  "NZ": "نیوزیلند",
  "NI": "نیکاراگوئه",
  "NE": "نیجر",
  "NG": "نیجریه",
  "NU": "نیووی",
  "NF": "جزیره نورفولک",
  "MP": "Northern Mariana Islands",
  "NO": "نروژ",
  "OM": "عمان",
  "PK": "پاکستان",
  "PW": "پالائو",
  "PS": "فلسطین",
  "PA": "پاناما",
  "PG": "پاپوآ گینه نو",
  "PY": "پاراگوئه",
  "PE": "پرو",
  "PH": "فیلیپین",
  "PN": "Pitcairn",
  "PL": "لهستان",
  "PT": "پرتغال",
  "PR": "پورتوریکو",
  "QA": "قطر",
  "RE": "رئونیون",
  "RO": "رومانی",
  "RU": "فدراسیون روسیه",
  "RW": "رواندا",
  "BL": "Saint Barthélemy",
  "SH": "Saint Helena, Ascension and Tristan da Cunha",
  "KN": "سنت کیتس و نویس",
  "LC": "سنت لوسیا",
  "MF": "سنت مارتین)",
  "PM": "سنت پیر و میکلون",
  "VC": "سنت وینسنت و گرنادین",
  "WS": "ساموآ",
  "SM": "سان مارینو",
  "ST": "سائو تومه و پرنسیپ,",
  "SA": "عربستان سعودی",
  "SN": "سنگال",
  "RS": "صربستان",
  "SC": "سیشل",
  "SL": "سیرالئون",
  "SG": "سنگاپور",
  "SX": "سینت مارتن)",
  "SK": "اسلواکی",
  "SI": "اسلوونی",
  "SB": "جزایر سلیمان",
  "SO": "سومالی",
  "ZA": "آفریقای جنوبی",
  "GS": "جورجیای جنوبی و جزایر ساندویچ جنوبی",
  "SS": "سودان جنوبی",
  "ES": "اسپانیا",
  "LK": "سریلانکا",
  "SD": "سودان",
  "SR": "سورینام",
  "SJ": "سوالبارد و یان ماین",
  "SZ": "سوازیلند",
  "SE": "سوئد",
  "CH": "سوئیس",
  "SY": "سوریه",
  "TW": "تایوان[یک]",
  "TJ": "تاجیکستان",
  "TZ": "ایالات متحده تانزانیا",
  "TH": "تایلند",
  "TL": "تیمور-لسته",
  "TG": "توگو",
  "TK": "توکلائو",
  "TO": "تونگا",
  "TT": "ترینیداد و توباگو",
  "TN": "تونس",
  "TR": "ترکیه",
  "TM": "ترکمنستان",
  "TC": "ترکس و کیاکوس",
  "TV": "تووالو",
  "UG": "اوگاندا",
  "UA": "اوکراین",
  "AE": "امارات متحده عربی",
  "GB": "پادشاهی متحده بریتانیا و ایرلند شمالی",
  "US": "ایالات متحده آمریکا",
  "UM": "جزایر کوچک حاشیهای ایالات متحده",
  "UY": "اروگوئه",
  "UZ": "ازبکستان",
  "VU": "وانواتو",
  "VE": "ونزوئلا (جمهوری بولیواری)",
  "VN": "ویتنام",
  "VG": "جزایر ویرجین (بریتانیا)",
  "VI": "جزایر ویرجین (ایالات متحده)",
  "WF": "والیس و فوتونا",
  "EH": "صحرای غربی",
  "YE": "یمن",
  "ZM": "زامبیا",
  "ZW": "زیمبابوه"
}